LICENSE
README.md
codestream/__init__.py
codestream/__main__.py
codestream/api/__init__.py
codestream/api/auth/__init__.py
codestream/api/blueprint/__init__.py
codestream/api/codestream/__init__.py
codestream/api/codestream/deployment.py
codestream/api/codestream/pipeline.py
codestream/api/codestream/swagger/examples/pipelinespec.json
codestream/api/codestream/swagger/schemas/_definitions.json
codestream/api/codestream/swagger/schemas/pipelinespec.json
codestream/api/codestream/variable.py
codestream/cli/__init__.py
codestream/cli/args.py
codestream/cli/command/__init__.py
codestream/cli/subcommands/__init__.py
codestream/cli/subcommands/blueprints.py
codestream/cli/subcommands/deployments.py
codestream/cli/subcommands/docs.py
codestream/cli/subcommands/pipelines/__init__.py
codestream/cli/subcommands/pipelines/check.py
codestream/cli/subcommands/pipelines/delete.py
codestream/cli/subcommands/pipelines/enable.py
codestream/cli/subcommands/pipelines/execute.py
codestream/cli/subcommands/pipelines/exports.py
codestream/cli/subcommands/pipelines/get.py
codestream/cli/subcommands/pipelines/imports.py
codestream/cli/subcommands/pipelines/validate.py
codestream/cli/subcommands/token.py
codestream/cli/subcommands/variables.py
codestream/common/__init__.py
codestream/common/config.py
codestream/common/config.yaml
codestream/common/exceptions.py
codestream/common/files.py
codestream/common/logger.py
codestream/common/rest.py
codestream/doco/__init__.py
codestream/gitlab/__init__.py
codestream_cli-1.0.1.dist-info/LICENSE
codestream_cli-1.0.1.dist-info/METADATA
codestream_cli-1.0.1.dist-info/WHEEL
codestream_cli-1.0.1.dist-info/entry_points.txt
codestream_cli-1.0.1.dist-info/RECORD
